LICENSE
MANIFEST.in
README.md
README.rst
play.py
setup.py
examples/midi_output.py
examples/simple.py
examples/threading.py
grid_instrument/__init__.py
grid_instrument/grid_instrument.py
grid_instrument.egg-info/PKG-INFO
grid_instrument.egg-info/SOURCES.txt
grid_instrument.egg-info/dependency_links.txt
grid_instrument.egg-info/requires.txt
grid_instrument.egg-info/top_level.txt