Metadata-Version: 1.0
Name: grid-instrument
Version: 0.6.3
Summary: Turn your Novation Launchpad into a MIDI instrument.
Home-page: https://github.com/dhilowitz/GridInstrument
Author: Dave Hilowitz
Author-email: dhilowitz@gmail.com
License: MIT License
Keywords: novation launchpad scales midi
Platform: UNKNOWN
